[
  {
    "name": "Wrapped Centrifuge",
    "slug": "wrapped-centrifuge",
    "symbol": "wcfg",
    "stats": {
      "contributors": 0,
      "dependents": 0,
      "forks": 0,
      "commits": 0
    }
  },
  {
    "name": "Spellfire",
    "slug": "spellfire-re-master-the-magic",
    "symbol": "spellfire",
    "stats": {
      "contributors": 0,
      "dependents": 0,
      "forks": 0,
      "commits": 0
    }
  },
  {
    "name": "Pollux Coin",
    "slug": "pollux-coin",
    "symbol": "pox",
    "stats": {
      "contributors": 0,
      "dependents": 0,
      "forks": 0,
      "commits": 0
    }
  },
  {
    "name": "Zombie Inu(New)",
    "slug": "zombie-inu-v2",
    "symbol": "zinu",
    "stats": {
      "contributors": 0,
      "dependents": 0,
      "forks": 0,
      "commits": 0
    }
  },
  {
    "name": "Klever Finance",
    "slug": "klever-finance",
    "symbol": "kfi",
    "stats": {
      "contributors": 0,
      "dependents": 0,
      "forks": 0,
      "commits": 0
    }
  },
  {
    "name": "Bonsai3",
    "slug": "bonsai3",
    "symbol": "seed",
    "stats": {
      "contributors": 0,
      "dependents": 0,
      "forks": 0,
      "commits": 0
    }
  },
  {
    "name": "KridaFans",
    "slug": "kridafans",
    "symbol": "krida",
    "stats": {
      "contributors": 0,
      "dependents": 0,
      "forks": 0,
      "commits": 0
    }
  },
  {
    "name": "StakeWise",
    "slug": "stakewise-reth2",
    "symbol": "reth2",
    "stats": {
      "contributors": 0,
      "dependents": 0,
      "forks": 0,
      "commits": 0
    }
  },
  {
    "name": "MicroMoney",
    "slug": "micromoney",
    "symbol": "amm",
    "stats": {
      "contributors": 0,
      "dependents": 0,
      "forks": 0,
      "commits": 0
    }
  },
  {
    "name": "XBIT",
    "slug": "4xbit",
    "symbol": "xbt",
    "stats": {
      "contributors": 0,
      "dependents": 0,
      "forks": 0,
      "commits": 0
    }
  },
  {
    "name": "IPMB",
    "slug": "ipmb",
    "symbol": "ipmb",
    "stats": {
      "contributors": 0,
      "dependents": 0,
      "forks": 0,
      "commits": 0
    }
  },
  {
    "name": "GOLCOIN",
    "slug": "golcoin",
    "symbol": "golc",
    "stats": {
      "contributors": 0,
      "dependents": 0,
      "forks": 0,
      "commits": 0
    }
  },
  {
    "name": "Panther Protocol",
    "slug": "panther-protocol",
    "symbol": "zkp",
    "stats": {
      "contributors": 0,
      "dependents": 0,
      "forks": 0,
      "commits": 0
    }
  },
  {
    "name": "Megaton Finance",
    "slug": "megaton-finance",
    "symbol": "mega",
    "stats": {
      "contributors": 0,
      "dependents": 0,
      "forks": 0,
      "commits": 0
    }
  },
  {
    "name": "Carmin",
    "slug": "carmin-labs",
    "symbol": "carmin",
    "stats": {
      "contributors": 0,
      "dependents": 0,
      "forks": 0,
      "commits": 0
    }
  },
  {
    "name": "EFK Token",
    "slug": "efk-token",
    "symbol": "efk",
    "stats": {
      "contributors": 0,
      "dependents": 0,
      "forks": 0,
      "commits": 0
    }
  },
  {
    "name": "UkraineDAO Flag NFT",
    "slug": "ukrainedao-flag-nft",
    "symbol": "love",
    "stats": {
      "contributors": 0,
      "dependents": 0,
      "forks": 0,
      "commits": 0
    }
  },
  {
    "name": "Veil",
    "slug": "veil-exchange",
    "symbol": "veil",
    "stats": {
      "contributors": 0,
      "dependents": 0,
      "forks": 0,
      "commits": 0
    }
  },
  {
    "name": "FintraDao",
    "slug": "fintradao",
    "symbol": "fdc",
    "stats": {
      "contributors": 0,
      "dependents": 0,
      "forks": 0,
      "commits": 0
    }
  },
  {
    "name": "KONPAY",
    "slug": "konpay",
    "symbol": "kon",
    "stats": {
      "contributors": 0,
      "dependents": 0,
      "forks": 0,
      "commits": 0
    }
  },
  {
    "name": "Sipher",
    "slug": "sipher",
    "symbol": "sipher",
    "stats": {
      "contributors": 0,
      "dependents": 0,
      "forks": 0,
      "commits": 0
    }
  },
  {
    "name": "Vector Finance",
    "slug": "vector-finance",
    "symbol": "vtx",
    "stats": {
      "contributors": 0,
      "dependents": 0,
      "forks": 0,
      "commits": 0
    }
  },
  {
    "name": "MoonStarter",
    "slug": "moonstarter",
    "symbol": "mnst",
    "stats": {
      "contributors": 0,
      "dependents": 0,
      "forks": 0,
      "commits": 0
    }
  },
  {
    "name": "Launchpool",
    "slug": "launchpool",
    "symbol": "lpool",
    "stats": {
      "contributors": 0,
      "dependents": 0,
      "forks": 0,
      "commits": 0
    }
  },
  {
    "name": "CHARTAI",
    "slug": "chartai",
    "symbol": "cx",
    "stats": {
      "contributors": 0,
      "dependents": 0,
      "forks": 0,
      "commits": 0
    }
  },
  {
    "name": "Mars Token",
    "slug": "mars-token",
    "symbol": "mrst",
    "stats": {
      "contributors": 0,
      "dependents": 0,
      "forks": 0,
      "commits": 0
    }
  },
  {
    "name": "Atlas DEX",
    "slug": "atlas-dex",
    "symbol": "ats",
    "stats": {
      "contributors": 0,
      "dependents": 0,
      "forks": 0,
      "commits": 0
    }
  },
  {
    "name": "World$tateCoin",
    "slug": "the-world-state",
    "symbol": "w$c",
    "stats": {
      "contributors": 0,
      "dependents": 0,
      "forks": 0,
      "commits": 0
    }
  },
  {
    "name": "Chad Coin",
    "slug": "chad-coin",
    "symbol": "chad",
    "stats": {
      "contributors": 0,
      "dependents": 0,
      "forks": 0,
      "commits": 0
    }
  },
  {
    "name": "Trice",
    "slug": "trice",
    "symbol": "tri",
    "stats": {
      "contributors": 0,
      "dependents": 0,
      "forks": 0,
      "commits": 0
    }
  },
  {
    "name": "DefiDollar",
    "slug": "defidollar",
    "symbol": "dusd",
    "stats": {
      "contributors": 0,
      "dependents": 0,
      "forks": 0,
      "commits": 0
    }
  },
  {
    "name": "CARD.STARTER",
    "slug": "card-starter",
    "symbol": "cards",
    "stats": {
      "contributors": 0,
      "dependents": 0,
      "forks": 0,
      "commits": 0
    }
  },
  {
    "name": "Kusunoki Samurai",
    "slug": "kusunoki-samurai",
    "symbol": "kusunoki",
    "stats": {
      "contributors": 0,
      "dependents": 0,
      "forks": 0,
      "commits": 0
    }
  },
  {
    "name": "Genesys",
    "slug": "genesys",
    "symbol": "gsys",
    "stats": {
      "contributors": 0,
      "dependents": 0,
      "forks": 0,
      "commits": 0
    }
  },
  {
    "name": "Fathom Dollar",
    "slug": "fathom-protocol",
    "symbol": "fxd",
    "stats": {
      "contributors": 0,
      "dependents": 0,
      "forks": 0,
      "commits": 0
    }
  },
  {
    "name": "ENCOINS",
    "slug": "encoins",
    "symbol": "encs",
    "stats": {
      "contributors": 0,
      "dependents": 0,
      "forks": 0,
      "commits": 0
    }
  },
  {
    "name": "MikeToken",
    "slug": "miketoken",
    "symbol": "mkt",
    "stats": {
      "contributors": 0,
      "dependents": 0,
      "forks": 0,
      "commits": 0
    }
  },
  {
    "name": "OGzClub",
    "slug": "ogzclub",
    "symbol": "ogz",
    "stats": {
      "contributors": 0,
      "dependents": 0,
      "forks": 0,
      "commits": 0
    }
  },
  {
    "name": "ASYAGRO",
    "slug": "asyagro",
    "symbol": "asy",
    "stats": {
      "contributors": 0,
      "dependents": 0,
      "forks": 0,
      "commits": 0
    }
  },
  {
    "name": "Orbit Bridge Klaytn Orbit Chain",
    "slug": "orbit-bridge-klaytn-orbit-chain",
    "symbol": "oorc",
    "stats": {
      "contributors": 0,
      "dependents": 0,
      "forks": 0,
      "commits": 0
    }
  },
  {
    "name": "Nexus Dubai",
    "slug": "nexus-dubai",
    "symbol": "nxd",
    "stats": {
      "contributors": 0,
      "dependents": 0,
      "forks": 0,
      "commits": 0
    }
  },
  {
    "name": "X Protocol",
    "slug": "x-protocol",
    "symbol": "pot",
    "stats": {
      "contributors": 0,
      "dependents": 0,
      "forks": 0,
      "commits": 0
    }
  },
  {
    "name": "Streakk Chain",
    "slug": "streakk-chain",
    "symbol": "stkc",
    "stats": {
      "contributors": 0,
      "dependents": 0,
      "forks": 0,
      "commits": 0
    }
  },
  {
    "name": "Grumpy",
    "slug": "grumpy",
    "symbol": "grum",
    "stats": {
      "contributors": 0,
      "dependents": 0,
      "forks": 0,
      "commits": 0
    }
  },
  {
    "name": "PandAI",
    "slug": "pandai",
    "symbol": "pandai",
    "stats": {
      "contributors": 0,
      "dependents": 0,
      "forks": 0,
      "commits": 0
    }
  },
  {
    "name": "KittyCake",
    "slug": "kittycake",
    "symbol": "kcake",
    "stats": {
      "contributors": 0,
      "dependents": 0,
      "forks": 0,
      "commits": 0
    }
  },
  {
    "name": "Turbos Finance",
    "slug": "turbos-finance",
    "symbol": "turbos",
    "stats": {
      "contributors": 0,
      "dependents": 0,
      "forks": 0,
      "commits": 0
    }
  },
  {
    "name": "FalconsInu",
    "slug": "falcon-swaps",
    "symbol": "falcons",
    "stats": {
      "contributors": 0,
      "dependents": 0,
      "forks": 0,
      "commits": 0
    }
  },
  {
    "name": "CPUcoin",
    "slug": "cpucoin",
    "symbol": "cpu",
    "stats": {
      "contributors": 0,
      "dependents": 0,
      "forks": 0,
      "commits": 0
    }
  },
  {
    "name": "Aureus Nummus Gold",
    "slug": "aureus-nummus-gold",
    "symbol": "ang",
    "stats": {
      "contributors": 0,
      "dependents": 0,
      "forks": 0,
      "commits": 0
    }
  }
]
