[
  {
    "name": "KStarNFT",
    "slug": "kstarnft",
    "symbol": "knft",
    "stats": {
      "contributors": 0,
      "dependents": 0,
      "forks": 0,
      "commits": 0
    }
  },
  {
    "name": "ZigZag",
    "slug": "zigzag",
    "symbol": "zz",
    "stats": {
      "contributors": 0,
      "dependents": 0,
      "forks": 0,
      "commits": 0
    }
  },
  {
    "name": "Metafluence",
    "slug": "metafluence",
    "symbol": "meto",
    "stats": {
      "contributors": 0,
      "dependents": 0,
      "forks": 0,
      "commits": 0
    }
  },
  {
    "name": "FractonX",
    "slug": "fracton-protocol",
    "symbol": "ft",
    "stats": {
      "contributors": 0,
      "dependents": 0,
      "forks": 0,
      "commits": 0
    }
  },
  {
    "name": "Pancake Games",
    "slug": "pancake-games",
    "symbol": "gcake",
    "stats": {
      "contributors": 0,
      "dependents": 0,
      "forks": 0,
      "commits": 0
    }
  },
  {
    "name": "Xi Token",
    "slug": "xi-token",
    "symbol": "xi",
    "stats": {
      "contributors": 0,
      "dependents": 0,
      "forks": 0,
      "commits": 0
    }
  },
  {
    "name": "NASDEX",
    "slug": "nasdex",
    "symbol": "nsdx",
    "stats": {
      "contributors": 0,
      "dependents": 0,
      "forks": 0,
      "commits": 0
    }
  },
  {
    "name": "Frax Staked Ether",
    "slug": "frax-staked-ether",
    "symbol": "sfrxeth",
    "stats": {
      "contributors": 0,
      "dependents": 0,
      "forks": 0,
      "commits": 0
    }
  },
  {
    "name": "Waggle Network",
    "slug": "waggle-network",
    "symbol": "wag",
    "stats": {
      "contributors": 0,
      "dependents": 0,
      "forks": 0,
      "commits": 0
    }
  },
  {
    "name": "Cloudname",
    "slug": "cloudname",
    "symbol": "cname",
    "stats": {
      "contributors": 0,
      "dependents": 0,
      "forks": 0,
      "commits": 0
    }
  },
  {
    "name": "VNX Gold",
    "slug": "vnx-gold",
    "symbol": "vnxau",
    "stats": {
      "contributors": 0,
      "dependents": 0,
      "forks": 0,
      "commits": 0
    }
  },
  {
    "name": "Arker",
    "slug": "arker",
    "symbol": "arker",
    "stats": {
      "contributors": 0,
      "dependents": 0,
      "forks": 0,
      "commits": 0
    }
  },
  {
    "name": "Lavita AI",
    "slug": "lavita-ai",
    "symbol": "lavita",
    "stats": {
      "contributors": 0,
      "dependents": 0,
      "forks": 0,
      "commits": 0
    }
  },
  {
    "name": "KingdomX",
    "slug": "kingdomx",
    "symbol": "kt",
    "stats": {
      "contributors": 0,
      "dependents": 0,
      "forks": 0,
      "commits": 0
    }
  },
  {
    "name": "Virtual Tourist",
    "slug": "virtual-tourist",
    "symbol": "vt",
    "stats": {
      "contributors": 0,
      "dependents": 0,
      "forks": 0,
      "commits": 0
    }
  },
  {
    "name": "Ness LAB",
    "slug": "ness-lab",
    "symbol": "ness",
    "stats": {
      "contributors": 0,
      "dependents": 0,
      "forks": 0,
      "commits": 0
    }
  },
  {
    "name": "Floyx",
    "slug": "floyx",
    "symbol": "floyx",
    "stats": {
      "contributors": 0,
      "dependents": 0,
      "forks": 0,
      "commits": 0
    }
  },
  {
    "name": "Distributed Autonomous Organization",
    "slug": "distributed-autonomous-organization",
    "symbol": "dao",
    "stats": {
      "contributors": 0,
      "dependents": 0,
      "forks": 0,
      "commits": 0
    }
  },
  {
    "name": "Italian National Football Team Fan Token",
    "slug": "italian-national-football-team-fan-token",
    "symbol": "ita",
    "stats": {
      "contributors": 0,
      "dependents": 0,
      "forks": 0,
      "commits": 0
    }
  },
  {
    "name": "BlockchainSpace",
    "slug": "blockchainspace",
    "symbol": "guild",
    "stats": {
      "contributors": 0,
      "dependents": 0,
      "forks": 0,
      "commits": 0
    }
  }
]
