[
  {
    "name": "Step App",
    "slug": "step-app",
    "symbol": "fitfi",
    "stats": {
      "contributors": 0,
      "dependents": 0,
      "forks": 0,
      "commits": 0
    }
  },
  {
    "name": "BurgerCities",
    "slug": "burger-cities",
    "symbol": "burger",
    "stats": {
      "contributors": 0,
      "dependents": 0,
      "forks": 0,
      "commits": 0
    }
  },
  {
    "name": "Pip",
    "slug": "pip",
    "symbol": "pip",
    "stats": {
      "contributors": 0,
      "dependents": 0,
      "forks": 0,
      "commits": 0
    }
  },
  {
    "name": "Everdome",
    "slug": "everdome",
    "symbol": "dome",
    "stats": {
      "contributors": 0,
      "dependents": 0,
      "forks": 0,
      "commits": 0
    }
  },
  {
    "name": "Zenon",
    "slug": "zenon",
    "symbol": "znn",
    "stats": {
      "contributors": 0,
      "dependents": 0,
      "forks": 0,
      "commits": 0
    }
  },
  {
    "name": "Decentral Games",
    "slug": "decentral-games",
    "symbol": "dg",
    "stats": {
      "contributors": 0,
      "dependents": 0,
      "forks": 0,
      "commits": 0
    }
  },
  {
    "name": "CoinEx Token",
    "slug": "coinex-token",
    "symbol": "cet",
    "stats": {
      "contributors": 0,
      "dependents": 0,
      "forks": 0,
      "commits": 0
    }
  },
  {
    "name": "Radiant",
    "slug": "radiant",
    "symbol": "rxd",
    "stats": {
      "contributors": 0,
      "dependents": 0,
      "forks": 0,
      "commits": 0
    }
  },
  {
    "name": "StaFi",
    "slug": "stafi",
    "symbol": "fis",
    "stats": {
      "contributors": 0,
      "dependents": 0,
      "forks": 0,
      "commits": 0
    }
  },
  {
    "name": "KILT Protocol",
    "slug": "kiltprotocol",
    "symbol": "kilt",
    "stats": {
      "contributors": 0,
      "dependents": 0,
      "forks": 0,
      "commits": 0
    }
  },
  {
    "name": "Alpine F1 Team Fan Token",
    "slug": "alpine-f1-team-fan-token",
    "symbol": "alpine",
    "stats": {
      "contributors": 0,
      "dependents": 0,
      "forks": 0,
      "commits": 0
    }
  },
  {
    "name": "Red Kite",
    "slug": "polkafoundry",
    "symbol": "pkf",
    "stats": {
      "contributors": 0,
      "dependents": 0,
      "forks": 0,
      "commits": 0
    }
  },
  {
    "name": "Castello Coin",
    "slug": "castello-coin",
    "symbol": "cast",
    "stats": {
      "contributors": 0,
      "dependents": 0,
      "forks": 0,
      "commits": 0
    }
  },
  {
    "name": "Decimated",
    "slug": "decimated",
    "symbol": "dio",
    "stats": {
      "contributors": 0,
      "dependents": 0,
      "forks": 0,
      "commits": 0
    }
  },
  {
    "name": "Petals",
    "slug": "petals",
    "symbol": "pts",
    "stats": {
      "contributors": 0,
      "dependents": 0,
      "forks": 0,
      "commits": 0
    }
  },
  {
    "name": "Bitcoin Diamond",
    "slug": "bitcoin-diamond",
    "symbol": "bcd",
    "stats": {
      "contributors": 0,
      "dependents": 0,
      "forks": 0,
      "commits": 0
    }
  },
  {
    "name": "TROY",
    "slug": "troy",
    "symbol": "troy",
    "stats": {
      "contributors": 0,
      "dependents": 0,
      "forks": 0,
      "commits": 0
    }
  },
  {
    "name": "Fulcrom Finance",
    "slug": "fulcrom-finance",
    "symbol": "ful",
    "stats": {
      "contributors": 0,
      "dependents": 0,
      "forks": 0,
      "commits": 0
    }
  },
  {
    "name": "pNetwork",
    "slug": "pnetwork",
    "symbol": "pnt",
    "stats": {
      "contributors": 0,
      "dependents": 0,
      "forks": 0,
      "commits": 0
    }
  },
  {
    "name": "Mango",
    "slug": "mango-markets",
    "symbol": "mngo",
    "stats": {
      "contributors": 0,
      "dependents": 0,
      "forks": 0,
      "commits": 0
    }
  }
]
