[
  {
    "name": "Wrapped Cardano",
    "slug": "wrapped-cardano",
    "symbol": "wada",
    "stats": {
      "contributors": 0,
      "dependents": 0,
      "forks": 0,
      "commits": 0
    }
  },
  {
    "name": "Conic Finance",
    "slug": "conic-finance",
    "symbol": "cnc",
    "stats": {
      "contributors": 0,
      "dependents": 0,
      "forks": 0,
      "commits": 0
    }
  },
  {
    "name": "PodFast",
    "slug": "podfast",
    "symbol": "fast",
    "stats": {
      "contributors": 0,
      "dependents": 0,
      "forks": 0,
      "commits": 0
    }
  },
  {
    "name": "Pegaxy",
    "slug": "pegaxy",
    "symbol": "pgx",
    "stats": {
      "contributors": 0,
      "dependents": 0,
      "forks": 0,
      "commits": 0
    }
  },
  {
    "name": "MOBIX",
    "slug": "mobix",
    "symbol": "mobx",
    "stats": {
      "contributors": 0,
      "dependents": 0,
      "forks": 0,
      "commits": 0
    }
  },
  {
    "name": "Safereum",
    "slug": "safereum",
    "symbol": "safereum",
    "stats": {
      "contributors": 0,
      "dependents": 0,
      "forks": 0,
      "commits": 0
    }
  },
  {
    "name": "MEMELORD",
    "slug": "memelord",
    "symbol": "lord",
    "stats": {
      "contributors": 0,
      "dependents": 0,
      "forks": 0,
      "commits": 0
    }
  },
  {
    "name": "ShibElon",
    "slug": "shibelon",
    "symbol": "shibelon",
    "stats": {
      "contributors": 0,
      "dependents": 0,
      "forks": 0,
      "commits": 0
    }
  },
  {
    "name": "Socean Staked Sol",
    "slug": "socean-staked-sol",
    "symbol": "scnsol",
    "stats": {
      "contributors": 0,
      "dependents": 0,
      "forks": 0,
      "commits": 0
    }
  },
  {
    "name": "Game Coin",
    "slug": "game-coin",
    "symbol": "gmex",
    "stats": {
      "contributors": 0,
      "dependents": 0,
      "forks": 0,
      "commits": 0
    }
  },
  {
    "name": "TCGCoin 2.0",
    "slug": "tcgcoin-2-0",
    "symbol": "tcg2",
    "stats": {
      "contributors": 0,
      "dependents": 0,
      "forks": 0,
      "commits": 0
    }
  },
  {
    "name": "DeHealth",
    "slug": "dehealth",
    "symbol": "dhlt",
    "stats": {
      "contributors": 0,
      "dependents": 0,
      "forks": 0,
      "commits": 0
    }
  },
  {
    "name": "Altair",
    "slug": "altair",
    "symbol": "air",
    "stats": {
      "contributors": 0,
      "dependents": 0,
      "forks": 0,
      "commits": 0
    }
  },
  {
    "name": "SoonVerse",
    "slug": "soonswap",
    "symbol": "soon",
    "stats": {
      "contributors": 0,
      "dependents": 0,
      "forks": 0,
      "commits": 0
    }
  },
  {
    "name": "Ivy Live",
    "slug": "ivy-live",
    "symbol": "ivy",
    "stats": {
      "contributors": 0,
      "dependents": 0,
      "forks": 0,
      "commits": 0
    }
  },
  {
    "name": "Nova finance",
    "slug": "nova-finance",
    "symbol": "nova",
    "stats": {
      "contributors": 0,
      "dependents": 0,
      "forks": 0,
      "commits": 0
    }
  },
  {
    "name": "Cheems",
    "slug": "cheems-token",
    "symbol": "cheems",
    "stats": {
      "contributors": 0,
      "dependents": 0,
      "forks": 0,
      "commits": 0
    }
  },
  {
    "name": "Akitavax",
    "slug": "akitavax",
    "symbol": "akitax",
    "stats": {
      "contributors": 0,
      "dependents": 0,
      "forks": 0,
      "commits": 0
    }
  },
  {
    "name": "French Connection Finance",
    "slug": "french-connection-finance",
    "symbol": "fcf",
    "stats": {
      "contributors": 0,
      "dependents": 0,
      "forks": 0,
      "commits": 0
    }
  },
  {
    "name": "Day Of Defeat 2.0",
    "slug": "day-of-defeat",
    "symbol": "dod",
    "stats": {
      "contributors": 0,
      "dependents": 0,
      "forks": 0,
      "commits": 0
    }
  }
]
