[
  {
    "name": "OctaSpace",
    "slug": "octaspace",
    "symbol": "octa",
    "stats": {
      "contributors": 0,
      "dependents": 0,
      "forks": 0,
      "commits": 0
    }
  },
  {
    "name": "Wall Street Bets (WSB)",
    "slug": "wall-street-bets-wsb",
    "symbol": "wsb",
    "stats": {
      "contributors": 0,
      "dependents": 0,
      "forks": 0,
      "commits": 0
    }
  },
  {
    "name": "Dash 2 Trade",
    "slug": "dash-trade",
    "symbol": "d2t",
    "stats": {
      "contributors": 0,
      "dependents": 0,
      "forks": 0,
      "commits": 0
    }
  },
  {
    "name": "Wojak 2.69",
    "slug": "wojak-269",
    "symbol": "wojak2.69",
    "stats": {
      "contributors": 0,
      "dependents": 0,
      "forks": 0,
      "commits": 0
    }
  },
  {
    "name": "Rubic",
    "slug": "rubic",
    "symbol": "rbc",
    "stats": {
      "contributors": 0,
      "dependents": 0,
      "forks": 0,
      "commits": 0
    }
  },
  {
    "name": "Brillion",
    "slug": "dua-token",
    "symbol": "dua",
    "stats": {
      "contributors": 0,
      "dependents": 0,
      "forks": 0,
      "commits": 0
    }
  },
  {
    "name": "OTSea",
    "slug": "otsea",
    "symbol": "otsea",
    "stats": {
      "contributors": 0,
      "dependents": 0,
      "forks": 0,
      "commits": 0
    }
  },
  {
    "name": "FitBurn",
    "slug": "fitburn",
    "symbol": "cal",
    "stats": {
      "contributors": 0,
      "dependents": 0,
      "forks": 0,
      "commits": 0
    }
  },
  {
    "name": "Hebeto",
    "slug": "hebeto",
    "symbol": "hbt",
    "stats": {
      "contributors": 0,
      "dependents": 0,
      "forks": 0,
      "commits": 0
    }
  },
  {
    "name": "HXRO",
    "slug": "hxro",
    "symbol": "hxro",
    "stats": {
      "contributors": 0,
      "dependents": 0,
      "forks": 0,
      "commits": 0
    }
  },
  {
    "name": "CrossFi",
    "slug": "mineplex-2",
    "symbol": "xfi",
    "stats": {
      "contributors": 0,
      "dependents": 0,
      "forks": 0,
      "commits": 0
    }
  },
  {
    "name": "Occam.Fi",
    "slug": "occamfi",
    "symbol": "occ",
    "stats": {
      "contributors": 0,
      "dependents": 0,
      "forks": 0,
      "commits": 0
    }
  },
  {
    "name": "Pi",
    "slug": "pinetwork",
    "symbol": "pi",
    "stats": {
      "contributors": 0,
      "dependents": 0,
      "forks": 0,
      "commits": 0
    }
  },
  {
    "name": "Liqwid Finance",
    "slug": "liqwid-finance",
    "symbol": "lq",
    "stats": {
      "contributors": 0,
      "dependents": 0,
      "forks": 0,
      "commits": 0
    }
  },
  {
    "name": "Weavers Token",
    "slug": "weavers-token",
    "symbol": "vrs",
    "stats": {
      "contributors": 0,
      "dependents": 0,
      "forks": 0,
      "commits": 0
    }
  },
  {
    "name": "Globiance Exchange Token",
    "slug": "globiance-exchange-token",
    "symbol": "gbex",
    "stats": {
      "contributors": 0,
      "dependents": 0,
      "forks": 0,
      "commits": 0
    }
  },
  {
    "name": "MEFLEX",
    "slug": "meflex",
    "symbol": "mef",
    "stats": {
      "contributors": 0,
      "dependents": 0,
      "forks": 0,
      "commits": 0
    }
  },
  {
    "name": "MetaQ",
    "slug": "metaq",
    "symbol": "metaq",
    "stats": {
      "contributors": 0,
      "dependents": 0,
      "forks": 0,
      "commits": 0
    }
  },
  {
    "name": "CDbio",
    "slug": "cdbio",
    "symbol": "mcd",
    "stats": {
      "contributors": 0,
      "dependents": 0,
      "forks": 0,
      "commits": 0
    }
  },
  {
    "name": "BITICA COIN",
    "slug": "bdcc-bitica-coin",
    "symbol": "bdcc",
    "stats": {
      "contributors": 0,
      "dependents": 0,
      "forks": 0,
      "commits": 0
    }
  },
  {
    "name": "UGOLD Inc.",
    "slug": "ugold-inc",
    "symbol": "ugold",
    "stats": {
      "contributors": 0,
      "dependents": 0,
      "forks": 0,
      "commits": 0
    }
  },
  {
    "name": "Hyper Pay",
    "slug": "hyper-pay",
    "symbol": "hpy",
    "stats": {
      "contributors": 0,
      "dependents": 0,
      "forks": 0,
      "commits": 0
    }
  },
  {
    "name": "Archway",
    "slug": "archway",
    "symbol": "arch",
    "stats": {
      "contributors": 0,
      "dependents": 0,
      "forks": 0,
      "commits": 0
    }
  },
  {
    "name": "Race Kingdom",
    "slug": "race-kingdom",
    "symbol": "atoz",
    "stats": {
      "contributors": 0,
      "dependents": 0,
      "forks": 0,
      "commits": 0
    }
  },
  {
    "name": "UwU Lend",
    "slug": "uwu-lend",
    "symbol": "uwu",
    "stats": {
      "contributors": 0,
      "dependents": 0,
      "forks": 0,
      "commits": 0
    }
  },
  {
    "name": "HyperCycle",
    "slug": "hypercycle",
    "symbol": "hypc",
    "stats": {
      "contributors": 0,
      "dependents": 0,
      "forks": 0,
      "commits": 0
    }
  },
  {
    "name": "LunaOne",
    "slug": "lunaone",
    "symbol": "xln",
    "stats": {
      "contributors": 0,
      "dependents": 0,
      "forks": 0,
      "commits": 0
    }
  },
  {
    "name": "EOS Force",
    "slug": "eos-force",
    "symbol": "eosc",
    "stats": {
      "contributors": 0,
      "dependents": 0,
      "forks": 0,
      "commits": 0
    }
  },
  {
    "name": "Ozonechain",
    "slug": "ozonechain",
    "symbol": "ozone",
    "stats": {
      "contributors": 0,
      "dependents": 0,
      "forks": 0,
      "commits": 0
    }
  },
  {
    "name": "Bware",
    "slug": "bware-labs",
    "symbol": "infra",
    "stats": {
      "contributors": 0,
      "dependents": 0,
      "forks": 0,
      "commits": 0
    }
  },
  {
    "name": "Stader BNBx",
    "slug": "stader-bnbx",
    "symbol": "bnbx",
    "stats": {
      "contributors": 0,
      "dependents": 0,
      "forks": 0,
      "commits": 0
    }
  },
  {
    "name": "BMAX",
    "slug": "bmax",
    "symbol": "bmax",
    "stats": {
      "contributors": 0,
      "dependents": 0,
      "forks": 0,
      "commits": 0
    }
  },
  {
    "name": "Ref Finance",
    "slug": "ref-finance",
    "symbol": "ref",
    "stats": {
      "contributors": 0,
      "dependents": 0,
      "forks": 0,
      "commits": 0
    }
  },
  {
    "name": "AshSwap",
    "slug": "ashswap",
    "symbol": "ash",
    "stats": {
      "contributors": 0,
      "dependents": 0,
      "forks": 0,
      "commits": 0
    }
  },
  {
    "name": "AS Monaco Fan Token",
    "slug": "as-monaco-fan-token",
    "symbol": "asm",
    "stats": {
      "contributors": 0,
      "dependents": 0,
      "forks": 0,
      "commits": 0
    }
  },
  {
    "name": "Mozaic",
    "slug": "mozaic",
    "symbol": "moz",
    "stats": {
      "contributors": 0,
      "dependents": 0,
      "forks": 0,
      "commits": 0
    }
  },
  {
    "name": "Coloniume Network",
    "slug": "coloniume-network",
    "symbol": "clnx",
    "stats": {
      "contributors": 0,
      "dependents": 0,
      "forks": 0,
      "commits": 0
    }
  },
  {
    "name": "Cyber Truck",
    "slug": "cyber-truck",
    "symbol": "cybertruck",
    "stats": {
      "contributors": 0,
      "dependents": 0,
      "forks": 0,
      "commits": 0
    }
  },
  {
    "name": "DarkShield Games Studio",
    "slug": "darkshield",
    "symbol": "dks",
    "stats": {
      "contributors": 0,
      "dependents": 0,
      "forks": 0,
      "commits": 0
    }
  },
  {
    "name": "Ruby Currency",
    "slug": "ruby-currency",
    "symbol": "rbc",
    "stats": {
      "contributors": 0,
      "dependents": 0,
      "forks": 0,
      "commits": 0
    }
  },
  {
    "name": "Vault Tech",
    "slug": "vault-tech",
    "symbol": "vault",
    "stats": {
      "contributors": 0,
      "dependents": 0,
      "forks": 0,
      "commits": 0
    }
  },
  {
    "name": "Metanept",
    "slug": "metanept",
    "symbol": "nept",
    "stats": {
      "contributors": 0,
      "dependents": 0,
      "forks": 0,
      "commits": 0
    }
  },
  {
    "name": "BIDZ Coin",
    "slug": "bidz-coin",
    "symbol": "bidz",
    "stats": {
      "contributors": 0,
      "dependents": 0,
      "forks": 0,
      "commits": 0
    }
  },
  {
    "name": "FXDX",
    "slug": "fxdx-exchange",
    "symbol": "fxdx",
    "stats": {
      "contributors": 0,
      "dependents": 0,
      "forks": 0,
      "commits": 0
    }
  },
  {
    "name": "Moonsama",
    "slug": "exosama-network",
    "symbol": "sama",
    "stats": {
      "contributors": 0,
      "dependents": 0,
      "forks": 0,
      "commits": 0
    }
  },
  {
    "name": "Realm",
    "slug": "realm",
    "symbol": "realm",
    "stats": {
      "contributors": 0,
      "dependents": 0,
      "forks": 0,
      "commits": 0
    }
  },
  {
    "name": "ParallelChain",
    "slug": "parallelchain",
    "symbol": "xpll",
    "stats": {
      "contributors": 0,
      "dependents": 0,
      "forks": 0,
      "commits": 0
    }
  },
  {
    "name": "Metano",
    "slug": "metano-foundations-token",
    "symbol": "metano",
    "stats": {
      "contributors": 0,
      "dependents": 0,
      "forks": 0,
      "commits": 0
    }
  },
  {
    "name": "AssetMantle",
    "slug": "assetmantle",
    "symbol": "mntl",
    "stats": {
      "contributors": 0,
      "dependents": 0,
      "forks": 0,
      "commits": 0
    }
  },
  {
    "name": "Jumbo Exchange",
    "slug": "jumbo-exchange",
    "symbol": "jumbo",
    "stats": {
      "contributors": 0,
      "dependents": 0,
      "forks": 0,
      "commits": 0
    }
  },
  {
    "name": "ShibaPoconk",
    "slug": "shibapoconk",
    "symbol": "conk",
    "stats": {
      "contributors": 0,
      "dependents": 0,
      "forks": 0,
      "commits": 0
    }
  },
  {
    "name": "EquityPay",
    "slug": "equitypay",
    "symbol": "eqpay",
    "stats": {
      "contributors": 0,
      "dependents": 0,
      "forks": 0,
      "commits": 0
    }
  },
  {
    "name": "Galaxy Coin",
    "slug": "galaxycoin",
    "symbol": "galaxy",
    "stats": {
      "contributors": 0,
      "dependents": 0,
      "forks": 0,
      "commits": 0
    }
  },
  {
    "name": "CHAINMAIL",
    "slug": "chainmail",
    "symbol": "mail",
    "stats": {
      "contributors": 0,
      "dependents": 0,
      "forks": 0,
      "commits": 0
    }
  },
  {
    "name": "Planet IX(formerly IX token)",
    "slug": "ix-token",
    "symbol": "ixt",
    "stats": {
      "contributors": 0,
      "dependents": 0,
      "forks": 0,
      "commits": 0
    }
  },
  {
    "name": "Xahau",
    "slug": "xahau",
    "symbol": "xah",
    "stats": {
      "contributors": 0,
      "dependents": 0,
      "forks": 0,
      "commits": 0
    }
  },
  {
    "name": "Savings Dai",
    "slug": "savings-dai",
    "symbol": "sdai",
    "stats": {
      "contributors": 0,
      "dependents": 0,
      "forks": 0,
      "commits": 0
    }
  },
  {
    "name": "The Debt Box",
    "slug": "the-debt-box",
    "symbol": "debt",
    "stats": {
      "contributors": 0,
      "dependents": 0,
      "forks": 0,
      "commits": 0
    }
  },
  {
    "name": "Leia",
    "slug": "leia",
    "symbol": "leia",
    "stats": {
      "contributors": 0,
      "dependents": 0,
      "forks": 0,
      "commits": 0
    }
  },
  {
    "name": "GM Wagmi",
    "slug": "gm",
    "symbol": "gm",
    "stats": {
      "contributors": 0,
      "dependents": 0,
      "forks": 0,
      "commits": 0
    }
  },
  {
    "name": "FUNCH",
    "slug": "funch-app",
    "symbol": "funch",
    "stats": {
      "contributors": 0,
      "dependents": 0,
      "forks": 0,
      "commits": 0
    }
  },
  {
    "name": "THORSwap",
    "slug": "thorswap",
    "symbol": "thor",
    "stats": {
      "contributors": 0,
      "dependents": 0,
      "forks": 0,
      "commits": 0
    }
  },
  {
    "name": "Epillo",
    "slug": "epillo",
    "symbol": "epillo",
    "stats": {
      "contributors": 0,
      "dependents": 0,
      "forks": 0,
      "commits": 0
    }
  },
  {
    "name": "GreenWorld",
    "slug": "greenworld",
    "symbol": "gwd",
    "stats": {
      "contributors": 0,
      "dependents": 0,
      "forks": 0,
      "commits": 0
    }
  },
  {
    "name": "CLIMBERS",
    "slug": "climbers",
    "symbol": "mithril",
    "stats": {
      "contributors": 0,
      "dependents": 0,
      "forks": 0,
      "commits": 0
    }
  },
  {
    "name": "Agoric",
    "slug": "agoric",
    "symbol": "bld",
    "stats": {
      "contributors": 0,
      "dependents": 0,
      "forks": 0,
      "commits": 0
    }
  },
  {
    "name": "Dopex",
    "slug": "dopex",
    "symbol": "dpx",
    "stats": {
      "contributors": 0,
      "dependents": 0,
      "forks": 0,
      "commits": 0
    }
  },
  {
    "name": "Silent Notary",
    "slug": "silent-notary",
    "symbol": "ubsn",
    "stats": {
      "contributors": 0,
      "dependents": 0,
      "forks": 0,
      "commits": 0
    }
  },
  {
    "name": "Sonne Finance",
    "slug": "sonne-finance",
    "symbol": "sonne",
    "stats": {
      "contributors": 0,
      "dependents": 0,
      "forks": 0,
      "commits": 0
    }
  },
  {
    "name": "BOMB",
    "slug": "bomb",
    "symbol": "bomb",
    "stats": {
      "contributors": 0,
      "dependents": 0,
      "forks": 0,
      "commits": 0
    }
  },
  {
    "name": "Non-Playable Coin",
    "slug": "non-playable-coin",
    "symbol": "npc",
    "stats": {
      "contributors": 0,
      "dependents": 0,
      "forks": 0,
      "commits": 0
    }
  },
  {
    "name": "Witnet",
    "slug": "witnet",
    "symbol": "wit",
    "stats": {
      "contributors": 0,
      "dependents": 0,
      "forks": 0,
      "commits": 0
    }
  },
  {
    "name": "Hosky Token",
    "slug": "hosky-token",
    "symbol": "hosky",
    "stats": {
      "contributors": 0,
      "dependents": 0,
      "forks": 0,
      "commits": 0
    }
  },
  {
    "name": "Froggy",
    "slug": "froggy",
    "symbol": "froggy",
    "stats": {
      "contributors": 0,
      "dependents": 0,
      "forks": 0,
      "commits": 0
    }
  },
  {
    "name": "Port Finance",
    "slug": "port-finance",
    "symbol": "port",
    "stats": {
      "contributors": 0,
      "dependents": 0,
      "forks": 0,
      "commits": 0
    }
  },
  {
    "name": "Jupiter",
    "slug": "jupiter",
    "symbol": "jup",
    "stats": {
      "contributors": 0,
      "dependents": 0,
      "forks": 0,
      "commits": 0
    }
  },
  {
    "name": "Love Earn Enjoy",
    "slug": "love-earn-enjoy",
    "symbol": "lee",
    "stats": {
      "contributors": 0,
      "dependents": 0,
      "forks": 0,
      "commits": 0
    }
  },
  {
    "name": "Open Source Network",
    "slug": "open-source-network",
    "symbol": "opn",
    "stats": {
      "contributors": 0,
      "dependents": 0,
      "forks": 0,
      "commits": 0
    }
  },
  {
    "name": "Zamio",
    "slug": "zamio",
    "symbol": "zam",
    "stats": {
      "contributors": 0,
      "dependents": 0,
      "forks": 0,
      "commits": 0
    }
  },
  {
    "name": "Media Network",
    "slug": "media-network",
    "symbol": "media",
    "stats": {
      "contributors": 0,
      "dependents": 0,
      "forks": 0,
      "commits": 0
    }
  },
  {
    "name": "FireStarter",
    "slug": "firestarter",
    "symbol": "flame",
    "stats": {
      "contributors": 0,
      "dependents": 0,
      "forks": 0,
      "commits": 0
    }
  },
  {
    "name": "UXD Protocol",
    "slug": "uxd-protocol",
    "symbol": "uxp",
    "stats": {
      "contributors": 0,
      "dependents": 0,
      "forks": 0,
      "commits": 0
    }
  },
  {
    "name": "ARCS",
    "slug": "arcs",
    "symbol": "arx",
    "stats": {
      "contributors": 0,
      "dependents": 0,
      "forks": 0,
      "commits": 0
    }
  },
  {
    "name": "Achain",
    "slug": "achain",
    "symbol": "act",
    "stats": {
      "contributors": 0,
      "dependents": 0,
      "forks": 0,
      "commits": 0
    }
  },
  {
    "name": "Yieldification",
    "slug": "yieldification",
    "symbol": "ydf",
    "stats": {
      "contributors": 0,
      "dependents": 0,
      "forks": 0,
      "commits": 0
    }
  },
  {
    "name": "TridentDAO",
    "slug": "tridentdao",
    "symbol": "psi",
    "stats": {
      "contributors": 0,
      "dependents": 0,
      "forks": 0,
      "commits": 0
    }
  },
  {
    "name": "Pacman",
    "slug": "pacman",
    "symbol": "pac",
    "stats": {
      "contributors": 0,
      "dependents": 0,
      "forks": 0,
      "commits": 0
    }
  },
  {
    "name": "Nova",
    "slug": "nova-ubi",
    "symbol": "nova",
    "stats": {
      "contributors": 0,
      "dependents": 0,
      "forks": 0,
      "commits": 0
    }
  },
  {
    "name": "Shimmer",
    "slug": "shimmer",
    "symbol": "smr",
    "stats": {
      "contributors": 0,
      "dependents": 0,
      "forks": 0,
      "commits": 0
    }
  },
  {
    "name": "Suzuverse",
    "slug": "suzuverse",
    "symbol": "sgt",
    "stats": {
      "contributors": 0,
      "dependents": 0,
      "forks": 0,
      "commits": 0
    }
  },
  {
    "name": "VEROX",
    "slug": "verox",
    "symbol": "vrx",
    "stats": {
      "contributors": 0,
      "dependents": 0,
      "forks": 0,
      "commits": 0
    }
  },
  {
    "name": "MContent",
    "slug": "mcontent",
    "symbol": "mcontent",
    "stats": {
      "contributors": 0,
      "dependents": 0,
      "forks": 0,
      "commits": 0
    }
  },
  {
    "name": "LORDS",
    "slug": "lords",
    "symbol": "lords",
    "stats": {
      "contributors": 0,
      "dependents": 0,
      "forks": 0,
      "commits": 0
    }
  },
  {
    "name": "TAP FANTASY",
    "slug": "tap-fantasy",
    "symbol": "tap",
    "stats": {
      "contributors": 0,
      "dependents": 0,
      "forks": 0,
      "commits": 0
    }
  },
  {
    "name": "EQIFI",
    "slug": "eqifi",
    "symbol": "eqx",
    "stats": {
      "contributors": 0,
      "dependents": 0,
      "forks": 0,
      "commits": 0
    }
  },
  {
    "name": "0 Knowledge Network",
    "slug": "0-knowledge-network",
    "symbol": "0kn",
    "stats": {
      "contributors": 0,
      "dependents": 0,
      "forks": 0,
      "commits": 0
    }
  },
  {
    "name": "Equation",
    "slug": "equation",
    "symbol": "equ",
    "stats": {
      "contributors": 0,
      "dependents": 0,
      "forks": 0,
      "commits": 0
    }
  },
  {
    "name": "ETHUP",
    "slug": "ethup",
    "symbol": "ethup",
    "stats": {
      "contributors": 0,
      "dependents": 0,
      "forks": 0,
      "commits": 0
    }
  },
  {
    "name": "Eternal World",
    "slug": "eternal-world",
    "symbol": "etl",
    "stats": {
      "contributors": 0,
      "dependents": 0,
      "forks": 0,
      "commits": 0
    }
  },
  {
    "name": "Level Finance",
    "slug": "level-finance",
    "symbol": "lvl",
    "stats": {
      "contributors": 0,
      "dependents": 0,
      "forks": 0,
      "commits": 0
    }
  },
  {
    "name": "Aquarius",
    "slug": "aquarius",
    "symbol": "aqua",
    "stats": {
      "contributors": 0,
      "dependents": 0,
      "forks": 0,
      "commits": 0
    }
  },
  {
    "name": "ONINO",
    "slug": "oni-token",
    "symbol": "oni",
    "stats": {
      "contributors": 0,
      "dependents": 0,
      "forks": 0,
      "commits": 0
    }
  },
  {
    "name": "Limoverse",
    "slug": "limoverse",
    "symbol": "limo",
    "stats": {
      "contributors": 0,
      "dependents": 0,
      "forks": 0,
      "commits": 0
    }
  },
  {
    "name": "Janex",
    "slug": "janex",
    "symbol": "jnx",
    "stats": {
      "contributors": 0,
      "dependents": 0,
      "forks": 0,
      "commits": 0
    }
  },
  {
    "name": "Rebuschain",
    "slug": "rebuschain",
    "symbol": "rebus",
    "stats": {
      "contributors": 0,
      "dependents": 0,
      "forks": 0,
      "commits": 0
    }
  },
  {
    "name": "Pomerium",
    "slug": "pomerium-ecosystem-token",
    "symbol": "pmg",
    "stats": {
      "contributors": 0,
      "dependents": 0,
      "forks": 0,
      "commits": 0
    }
  },
  {
    "name": "Allbridge",
    "slug": "allbridge",
    "symbol": "abr",
    "stats": {
      "contributors": 0,
      "dependents": 0,
      "forks": 0,
      "commits": 0
    }
  },
  {
    "name": "Mean DAO",
    "slug": "meanfi",
    "symbol": "mean",
    "stats": {
      "contributors": 0,
      "dependents": 0,
      "forks": 0,
      "commits": 0
    }
  },
  {
    "name": "Kondux",
    "slug": "kondux",
    "symbol": "kndx",
    "stats": {
      "contributors": 0,
      "dependents": 0,
      "forks": 0,
      "commits": 0
    }
  },
  {
    "name": "Baby Shiba Inu",
    "slug": "baby-shiba-inu-erc",
    "symbol": "babyshib",
    "stats": {
      "contributors": 0,
      "dependents": 0,
      "forks": 0,
      "commits": 0
    }
  },
  {
    "name": "Super Athletes Token",
    "slug": "super-athletes",
    "symbol": "sat",
    "stats": {
      "contributors": 0,
      "dependents": 0,
      "forks": 0,
      "commits": 0
    }
  },
  {
    "name": "LinkEye",
    "slug": "linkeye",
    "symbol": "let",
    "stats": {
      "contributors": 0,
      "dependents": 0,
      "forks": 0,
      "commits": 0
    }
  },
  {
    "name": "Tigres Fan Token",
    "slug": "tigres-fan-token",
    "symbol": "tigres",
    "stats": {
      "contributors": 0,
      "dependents": 0,
      "forks": 0,
      "commits": 0
    }
  },
  {
    "name": "Meter Stable",
    "slug": "meter-stable",
    "symbol": "mtr",
    "stats": {
      "contributors": 0,
      "dependents": 0,
      "forks": 0,
      "commits": 0
    }
  },
  {
    "name": "Crypto Real Estate",
    "slug": "crypto-real-estate",
    "symbol": "cre",
    "stats": {
      "contributors": 0,
      "dependents": 0,
      "forks": 0,
      "commits": 0
    }
  },
  {
    "name": "MTH Network",
    "slug": "mth-network",
    "symbol": "mthn",
    "stats": {
      "contributors": 0,
      "dependents": 0,
      "forks": 0,
      "commits": 0
    }
  },
  {
    "name": "Tectonic",
    "slug": "tectonic",
    "symbol": "tonic",
    "stats": {
      "contributors": 0,
      "dependents": 0,
      "forks": 0,
      "commits": 0
    }
  },
  {
    "name": "PaLM AI",
    "slug": "palm-ai",
    "symbol": "palm",
    "stats": {
      "contributors": 0,
      "dependents": 0,
      "forks": 0,
      "commits": 0
    }
  },
  {
    "name": "McPepe's",
    "slug": "mcpepes",
    "symbol": "pepes",
    "stats": {
      "contributors": 0,
      "dependents": 0,
      "forks": 0,
      "commits": 0
    }
  },
  {
    "name": "Cyberpunk City",
    "slug": "cyberpunk-city",
    "symbol": "cyber",
    "stats": {
      "contributors": 0,
      "dependents": 0,
      "forks": 0,
      "commits": 0
    }
  },
  {
    "name": "Wrapped IoTeX",
    "slug": "wrapped-iotex",
    "symbol": "wiotx",
    "stats": {
      "contributors": 0,
      "dependents": 0,
      "forks": 0,
      "commits": 0
    }
  },
  {
    "name": "Governance OHM",
    "slug": "governance-ohm",
    "symbol": "gohm",
    "stats": {
      "contributors": 0,
      "dependents": 0,
      "forks": 0,
      "commits": 0
    }
  },
  {
    "name": "Roko",
    "slug": "roko",
    "symbol": "roko",
    "stats": {
      "contributors": 0,
      "dependents": 0,
      "forks": 0,
      "commits": 0
    }
  },
  {
    "name": "Jim",
    "slug": "jim",
    "symbol": "jim",
    "stats": {
      "contributors": 0,
      "dependents": 0,
      "forks": 0,
      "commits": 0
    }
  },
  {
    "name": "Apricot Finance",
    "slug": "apricot",
    "symbol": "apt",
    "stats": {
      "contributors": 0,
      "dependents": 0,
      "forks": 0,
      "commits": 0
    }
  },
  {
    "name": "Soil",
    "slug": "soil",
    "symbol": "soil",
    "stats": {
      "contributors": 0,
      "dependents": 0,
      "forks": 0,
      "commits": 0
    }
  },
  {
    "name": "SteakHut Finance",
    "slug": "steakhut-finance",
    "symbol": "steak",
    "stats": {
      "contributors": 0,
      "dependents": 0,
      "forks": 0,
      "commits": 0
    }
  },
  {
    "name": "Clips",
    "slug": "clips-token",
    "symbol": "clips",
    "stats": {
      "contributors": 0,
      "dependents": 0,
      "forks": 0,
      "commits": 0
    }
  },
  {
    "name": "Materium",
    "slug": "materium",
    "symbol": "mtrm",
    "stats": {
      "contributors": 0,
      "dependents": 0,
      "forks": 0,
      "commits": 0
    }
  },
  {
    "name": "Bazed Games",
    "slug": "bazed-games",
    "symbol": "bazed",
    "stats": {
      "contributors": 0,
      "dependents": 0,
      "forks": 0,
      "commits": 0
    }
  },
  {
    "name": "SILK",
    "slug": "spider-tanks",
    "symbol": "silk",
    "stats": {
      "contributors": 0,
      "dependents": 0,
      "forks": 0,
      "commits": 0
    }
  },
  {
    "name": "C-cash",
    "slug": "c-cash",
    "symbol": "ccash",
    "stats": {
      "contributors": 0,
      "dependents": 0,
      "forks": 0,
      "commits": 0
    }
  },
  {
    "name": "Cappasity",
    "slug": "cappasity",
    "symbol": "capp",
    "stats": {
      "contributors": 0,
      "dependents": 0,
      "forks": 0,
      "commits": 0
    }
  },
  {
    "name": "SOUNI",
    "slug": "sovi-universe",
    "symbol": "son",
    "stats": {
      "contributors": 0,
      "dependents": 0,
      "forks": 0,
      "commits": 0
    }
  },
  {
    "name": "MAGA",
    "slug": "maga",
    "symbol": "trump",
    "stats": {
      "contributors": 0,
      "dependents": 0,
      "forks": 0,
      "commits": 0
    }
  },
  {
    "name": "FORE Protocol",
    "slug": "fore-protocol",
    "symbol": "fore",
    "stats": {
      "contributors": 0,
      "dependents": 0,
      "forks": 0,
      "commits": 0
    }
  },
  {
    "name": "AimBot",
    "slug": "aimbot",
    "symbol": "aimbot",
    "stats": {
      "contributors": 0,
      "dependents": 0,
      "forks": 0,
      "commits": 0
    }
  },
  {
    "name": "BinaryX (old)",
    "slug": "binaryx",
    "symbol": "bnx",
    "stats": {
      "contributors": 0,
      "dependents": 0,
      "forks": 0,
      "commits": 0
    }
  },
  {
    "name": "Divergence",
    "slug": "divergence",
    "symbol": "diver",
    "stats": {
      "contributors": 0,
      "dependents": 0,
      "forks": 0,
      "commits": 0
    }
  },
  {
    "name": "Metavault Trade",
    "slug": "metavault-trade",
    "symbol": "mvx",
    "stats": {
      "contributors": 0,
      "dependents": 0,
      "forks": 0,
      "commits": 0
    }
  },
  {
    "name": "Ridotto",
    "slug": "ridotto",
    "symbol": "rdt",
    "stats": {
      "contributors": 0,
      "dependents": 0,
      "forks": 0,
      "commits": 0
    }
  },
  {
    "name": "TryHards",
    "slug": "tryhards",
    "symbol": "try",
    "stats": {
      "contributors": 0,
      "dependents": 0,
      "forks": 0,
      "commits": 0
    }
  },
  {
    "name": "Jinbi Token",
    "slug": "jinbi-token",
    "symbol": "jnb",
    "stats": {
      "contributors": 0,
      "dependents": 0,
      "forks": 0,
      "commits": 0
    }
  },
  {
    "name": "TrustFi Network",
    "slug": "trustfi-network",
    "symbol": "tfi",
    "stats": {
      "contributors": 0,
      "dependents": 0,
      "forks": 0,
      "commits": 0
    }
  },
  {
    "name": "Pirichain",
    "slug": "pirichain",
    "symbol": "piri",
    "stats": {
      "contributors": 0,
      "dependents": 0,
      "forks": 0,
      "commits": 0
    }
  },
  {
    "name": "Ribbit",
    "slug": "ribbit-meme",
    "symbol": "ribbit",
    "stats": {
      "contributors": 0,
      "dependents": 0,
      "forks": 0,
      "commits": 0
    }
  },
  {
    "name": "Brickken",
    "slug": "brickken",
    "symbol": "bkn",
    "stats": {
      "contributors": 0,
      "dependents": 0,
      "forks": 0,
      "commits": 0
    }
  },
  {
    "name": "DEDPRZ",
    "slug": "dedprz-entertainment",
    "symbol": "usa",
    "stats": {
      "contributors": 0,
      "dependents": 0,
      "forks": 0,
      "commits": 0
    }
  },
  {
    "name": "Redacted",
    "slug": "redacted",
    "symbol": "btrfly",
    "stats": {
      "contributors": 0,
      "dependents": 0,
      "forks": 0,
      "commits": 0
    }
  },
  {
    "name": "Hadeswap",
    "slug": "hadeswap",
    "symbol": "hades",
    "stats": {
      "contributors": 0,
      "dependents": 0,
      "forks": 0,
      "commits": 0
    }
  },
  {
    "name": "Franklin",
    "slug": "franklin",
    "symbol": "fly",
    "stats": {
      "contributors": 0,
      "dependents": 0,
      "forks": 0,
      "commits": 0
    }
  },
  {
    "name": "Lucky Coin",
    "slug": "lucky-coin",
    "symbol": "lkc",
    "stats": {
      "contributors": 0,
      "dependents": 0,
      "forks": 0,
      "commits": 0
    }
  },
  {
    "name": "BNBDOWN",
    "slug": "bnbdown",
    "symbol": "bnbdown",
    "stats": {
      "contributors": 0,
      "dependents": 0,
      "forks": 0,
      "commits": 0
    }
  },
  {
    "name": "D3D Social",
    "slug": "d3d-social",
    "symbol": "d3d",
    "stats": {
      "contributors": 0,
      "dependents": 0,
      "forks": 0,
      "commits": 0
    }
  },
  {
    "name": "Whole Earth Coin",
    "slug": "whole-earth-coin",
    "symbol": "wec",
    "stats": {
      "contributors": 0,
      "dependents": 0,
      "forks": 0,
      "commits": 0
    }
  },
  {
    "name": "TARALITY",
    "slug": "tarality-v2",
    "symbol": "taral",
    "stats": {
      "contributors": 0,
      "dependents": 0,
      "forks": 0,
      "commits": 0
    }
  },
  {
    "name": "Fileshare Platform",
    "slug": "fileshare-platform",
    "symbol": "fsc",
    "stats": {
      "contributors": 0,
      "dependents": 0,
      "forks": 0,
      "commits": 0
    }
  },
  {
    "name": "Arbitrove Protocol",
    "slug": "nitro-cartel",
    "symbol": "trove",
    "stats": {
      "contributors": 0,
      "dependents": 0,
      "forks": 0,
      "commits": 0
    }
  },
  {
    "name": "Bullieverse",
    "slug": "bullieverse",
    "symbol": "$bull",
    "stats": {
      "contributors": 0,
      "dependents": 0,
      "forks": 0,
      "commits": 0
    }
  },
  {
    "name": "Neoxa",
    "slug": "neoxa",
    "symbol": "neox",
    "stats": {
      "contributors": 0,
      "dependents": 0,
      "forks": 0,
      "commits": 0
    }
  },
  {
    "name": "PEEPO",
    "slug": "peepo",
    "symbol": "peepo",
    "stats": {
      "contributors": 0,
      "dependents": 0,
      "forks": 0,
      "commits": 0
    }
  },
  {
    "name": "Perion",
    "slug": "perion",
    "symbol": "perc",
    "stats": {
      "contributors": 0,
      "dependents": 0,
      "forks": 0,
      "commits": 0
    }
  },
  {
    "name": "Oshi Token",
    "slug": "phantom-of-the-kill-alternative-imitation",
    "symbol": "oshi",
    "stats": {
      "contributors": 0,
      "dependents": 0,
      "forks": 0,
      "commits": 0
    }
  },
  {
    "name": "KINGU",
    "slug": "kingu",
    "symbol": "kingu",
    "stats": {
      "contributors": 0,
      "dependents": 0,
      "forks": 0,
      "commits": 0
    }
  },
  {
    "name": "Utility Cjournal",
    "slug": "utility-cjournal",
    "symbol": "ucjl",
    "stats": {
      "contributors": 0,
      "dependents": 0,
      "forks": 0,
      "commits": 0
    }
  },
  {
    "name": "Fanzee",
    "slug": "fanzee",
    "symbol": "fnz",
    "stats": {
      "contributors": 0,
      "dependents": 0,
      "forks": 0,
      "commits": 0
    }
  },
  {
    "name": "Wrapped Kaspa",
    "slug": "wrapped-kaspa",
    "symbol": "wkas",
    "stats": {
      "contributors": 0,
      "dependents": 0,
      "forks": 0,
      "commits": 0
    }
  },
  {
    "name": "BTCUP",
    "slug": "btcup",
    "symbol": "btcup",
    "stats": {
      "contributors": 0,
      "dependents": 0,
      "forks": 0,
      "commits": 0
    }
  },
  {
    "name": "BH Network",
    "slug": "bh-network",
    "symbol": "bhat",
    "stats": {
      "contributors": 0,
      "dependents": 0,
      "forks": 0,
      "commits": 0
    }
  },
  {
    "name": "CRYN",
    "slug": "cryn",
    "symbol": "cryn",
    "stats": {
      "contributors": 0,
      "dependents": 0,
      "forks": 0,
      "commits": 0
    }
  },
  {
    "name": "MRHB DeFi Network",
    "slug": "marhabadefi",
    "symbol": "mrhb",
    "stats": {
      "contributors": 0,
      "dependents": 0,
      "forks": 0,
      "commits": 0
    }
  },
  {
    "name": "Loop Network",
    "slug": "loopnetwork",
    "symbol": "loop",
    "stats": {
      "contributors": 0,
      "dependents": 0,
      "forks": 0,
      "commits": 0
    }
  },
  {
    "name": "Inery",
    "slug": "inery",
    "symbol": "inr",
    "stats": {
      "contributors": 0,
      "dependents": 0,
      "forks": 0,
      "commits": 0
    }
  },
  {
    "name": "Empyreal Exchange",
    "slug": "empyreal-exchange",
    "symbol": "emp",
    "stats": {
      "contributors": 0,
      "dependents": 0,
      "forks": 0,
      "commits": 0
    }
  },
  {
    "name": "Uhive",
    "slug": "uhive",
    "symbol": "hve2",
    "stats": {
      "contributors": 0,
      "dependents": 0,
      "forks": 0,
      "commits": 0
    }
  },
  {
    "name": "Vera",
    "slug": "vera-network",
    "symbol": "vera",
    "stats": {
      "contributors": 0,
      "dependents": 0,
      "forks": 0,
      "commits": 0
    }
  },
  {
    "name": "ExchangeCoin",
    "slug": "exchange-coin",
    "symbol": "excc",
    "stats": {
      "contributors": 0,
      "dependents": 0,
      "forks": 0,
      "commits": 0
    }
  },
  {
    "name": "HitBTC Token",
    "slug": "hitbtc-token",
    "symbol": "hit",
    "stats": {
      "contributors": 0,
      "dependents": 0,
      "forks": 0,
      "commits": 0
    }
  },
  {
    "name": "OMarket Global LLC",
    "slug": "openlive-nft",
    "symbol": "opv",
    "stats": {
      "contributors": 0,
      "dependents": 0,
      "forks": 0,
      "commits": 0
    }
  },
  {
    "name": "Renq Finance",
    "slug": "renq-finance",
    "symbol": "renq",
    "stats": {
      "contributors": 0,
      "dependents": 0,
      "forks": 0,
      "commits": 0
    }
  },
  {
    "name": "Droggy",
    "slug": "droggy",
    "symbol": "droggy",
    "stats": {
      "contributors": 0,
      "dependents": 0,
      "forks": 0,
      "commits": 0
    }
  },
  {
    "name": "Indigo Protocol - iBTC",
    "slug": "indigo-protocol-ibtc",
    "symbol": "ibtc",
    "stats": {
      "contributors": 0,
      "dependents": 0,
      "forks": 0,
      "commits": 0
    }
  },
  {
    "name": "BitcoinX",
    "slug": "bitcoinx-bxc",
    "symbol": "bxc",
    "stats": {
      "contributors": 0,
      "dependents": 0,
      "forks": 0,
      "commits": 0
    }
  },
  {
    "name": "Changer",
    "slug": "changer",
    "symbol": "cng",
    "stats": {
      "contributors": 0,
      "dependents": 0,
      "forks": 0,
      "commits": 0
    }
  },
  {
    "name": "ViCA Token",
    "slug": "vica-token",
    "symbol": "vica",
    "stats": {
      "contributors": 0,
      "dependents": 0,
      "forks": 0,
      "commits": 0
    }
  },
  {
    "name": "GLI TOKEN",
    "slug": "gli-token",
    "symbol": "gli",
    "stats": {
      "contributors": 0,
      "dependents": 0,
      "forks": 0,
      "commits": 0
    }
  },
  {
    "name": "Astroport",
    "slug": "astroport-fi",
    "symbol": "astro",
    "stats": {
      "contributors": 0,
      "dependents": 0,
      "forks": 0,
      "commits": 0
    }
  },
  {
    "name": "Chintai",
    "slug": "chex-token",
    "symbol": "chex",
    "stats": {
      "contributors": 0,
      "dependents": 0,
      "forks": 0,
      "commits": 0
    }
  },
  {
    "name": "Chumbi Valley",
    "slug": "chumbi-valley",
    "symbol": "chmb",
    "stats": {
      "contributors": 0,
      "dependents": 0,
      "forks": 0,
      "commits": 0
    }
  },
  {
    "name": "Starfish Finance",
    "slug": "starfish-finance",
    "symbol": "sean",
    "stats": {
      "contributors": 0,
      "dependents": 0,
      "forks": 0,
      "commits": 0
    }
  },
  {
    "name": "Honeyland",
    "slug": "honeyland",
    "symbol": "hxd",
    "stats": {
      "contributors": 0,
      "dependents": 0,
      "forks": 0,
      "commits": 0
    }
  },
  {
    "name": "CelebrityCoinV2",
    "slug": "celebritycoinv2",
    "symbol": "ccv2",
    "stats": {
      "contributors": 0,
      "dependents": 0,
      "forks": 0,
      "commits": 0
    }
  },
  {
    "name": "Degree Crypto Token",
    "slug": "degree-crypto-token",
    "symbol": "dct",
    "stats": {
      "contributors": 0,
      "dependents": 0,
      "forks": 0,
      "commits": 0
    }
  },
  {
    "name": "Relation Labs",
    "slug": "relation-labs",
    "symbol": "rel",
    "stats": {
      "contributors": 0,
      "dependents": 0,
      "forks": 0,
      "commits": 0
    }
  },
  {
    "name": "Meta Dance",
    "slug": "meta-dance",
    "symbol": "mdt",
    "stats": {
      "contributors": 0,
      "dependents": 0,
      "forks": 0,
      "commits": 0
    }
  },
  {
    "name": "Jeff World",
    "slug": "jeff-world",
    "symbol": "jeff",
    "stats": {
      "contributors": 0,
      "dependents": 0,
      "forks": 0,
      "commits": 0
    }
  },
  {
    "name": "Storepay",
    "slug": "storepay",
    "symbol": "spc",
    "stats": {
      "contributors": 0,
      "dependents": 0,
      "forks": 0,
      "commits": 0
    }
  },
  {
    "name": "Wrapped Ampleforth",
    "slug": "wrapped-ampleforth",
    "symbol": "wampl",
    "stats": {
      "contributors": 0,
      "dependents": 0,
      "forks": 0,
      "commits": 0
    }
  },
  {
    "name": "ChainEx",
    "slug": "chainex",
    "symbol": "cex",
    "stats": {
      "contributors": 0,
      "dependents": 0,
      "forks": 0,
      "commits": 0
    }
  },
  {
    "name": "Metaland Shares",
    "slug": "pikaster",
    "symbol": "mls",
    "stats": {
      "contributors": 0,
      "dependents": 0,
      "forks": 0,
      "commits": 0
    }
  }
]
